[{"place_id": 243961791, "licence": "Data \u00a9 OpenStreetMap contributors, ODbL 1.0. https://osm.org/copyright", "osm_type": "way", "osm_id": 723313901, "boundingbox": ["37.5607591", "37.5609557", "-122.2741702", "-122.2739387"], "lat": "37.560839650000005", "lon": "-122.27403725777779", "display_name": "Noah's Bagels, 1000D, Metro Center Boulevard, Foster City, San Mateo County, California, 94404, United States", "class": "amenity", "type": "fast_food", "importance": 0.101, "icon": "https://nominatim.openstreetmap.org/ui/mapicons//food_fastfood.p.20.png", "geojson": {"type": "Polygon", "coordinates": [[[-122.2741702, 37.5608946], [-122.2741566, 37.5608806], [-122.2740393, 37.5607591], [-122.273989, 37.5607897], [-122.2739387, 37.5608202], [-122.2739762, 37.5608591], [-122.2740515, 37.560937], [-122.2740696, 37.5609557], [-122.2741702, 37.5608946]]]}}]